{"type":"PR","pr":{"number":171,"head":"37121f83af9ba3e89ee96af2165f7c01ce34bd7d"},"user":"atjiujitsunyc","status":"draft","branch":"cms/kettlebell","collection":"pages","title":"KettleBell","description":"For toning and strengthening, try our new Kettlebell class! ","objects":{"entry":{"path":"content/pages/kettlebell.md","sha":"89dcc49310cc86b9e8e369edf6c4872d8ae5a39c"},"files":[{"path":"/static/img/dsc04886.jpg","sha":"16d458a776fa72b0b4c006c3f812b25198d08d1a"},{"path":"/static/img/dsc04938.jpg","sha":"9ff4f99b5ee5dc2dfed97b33d75c3ffad90ef1e1"}]},"timeStamp":"2020-02-01T15:39:24.640Z"}